Workbook

Sheet Projects Instruction
A1: PR. 1 Fundamental Booster
A2: Topics: - Relative & Absolute References, Formatting, Data Input - IF Formulas, Nested IFs, IF with AND/OR - COUNTIFS, SUMIFS, AVERAGEIFS - Lookup Functions (VLOOKUP, XLOOKUP, XMATCH) - INDEX/MATCH for dynamic searches - TEXT Functions for string manipulations - INDIRECT and OFFSET for dynamic references - Date/Time, Math Functions, FILTER function Main Tasks: 1. Apply IF formulas to classify student grades. 2. Use COUNTIFS to count students scoring above 60. 3. Use VLOOKUP to find a product price from sales data. 4. Apply XLOOKUP to fetch employee salaries dynamically. 5. Format and analyze date of joining in Employee data. 6. Use FILTER function to extract students with grades above 80. Deliverable: Complete the given worksheets by applying the required formulas in respective sheets.
A5: Essential Tasks
A6: Relative & Absolute Cell References, Formatting, and Data Input
A7: Enter and format data (bold, italic, currency, date, custom formats).
A8: Use absolute ($A$1) and relative (A1) references in formulas.
A10: Using IF Formula & Nesting IF Formulas
A11: Classify students' grades based on their scores.
A12: Compute discounts for sales based on price thresholds.
A14: Using IF with AND/OR Formulas
A15: Identify students who scored above 80 in both Math & Science using IF(AND(...)).
A16: Determine whether a product is eligible for discount using IF(OR(...)).
... A56: Extract a list of top-performing students based on scores.

Sheet Students Grade
A1: Student ID | B1: Name | C1: Math | D1: Science | E1: English | F1: Enrollment Date | G1: Average Marks | H1: Grades | I1: Pass/ fail | J1: Count Above 60 marks | K1: Countifs | L1: Above 80 math & science apply if OR & And
A2: 1002 | B2: Student 2 | C2: 78 | D2: 76 | E2: 70 | F2: 43281 | G2: =AVERAGE(C2:E2) -> 74.666667 | H2: =IF(G2>=75,"A", IF(G2>=60,"B", IF(G2>=35,"C","F"))) -> B | I2: =IF('Students Grade'!$G2>=35,"Pass","Fail") -> Pass | J2: =COUNTIF(G2:G20,">60") -> 15 | K2: =COUNTIFS(C2:C20,">50") -> 18 | L2: =IF(OR(C2>=90,D2>=90,E2>=90),"Eligible","Not Eligible") -> Not Eligible
A3: 1003 | B3: Student 3 | C3: 97 | D3: 60 | E3: 51 | F3: 43461 | G3: =AVERAGE(C3:E3) -> 69.333333 | H3: =IF(G3>=75,"A", IF(G3>=60,"B", IF(G3>=35,"C","F"))) -> B | I3: =IF('Students Grade'!$G3>=35,"Pass","Fail") -> Pass | J3: =COUNTIF(G3:G21,">60") -> 14 | K3: =COUNTIFS(C3:C21,">50") -> 17 | L3: =IF(OR(C3>=90,D3>=90,E3>=90),"Eligible","Not Eligible") -> Eligible
A4: 1004 | B4: Student 4 | C4: 74 | D4: 55 | E4: 46 | F4: 43641 | G4: =AVERAGE(C4:E4) -> 58.333333 | H4: =IF(G4>=75,"A", IF(G4>=60,"B", IF(G4>=35,"C","F"))) -> C | I4: =IF('Students Grade'!$G4>=35,"Pass","Fail") -> Pass | J4: =COUNTIF(G4:G21,">60") -> 13 | K4: =COUNTIFS(C4:C22,">50") -> 16 | L4: =IF(OR(C4>=90,D4>=90,E4>=90),"Eligible","Not Eligible") -> Not Eligible
A5: 1005 | B5: Student 5 | C5: 68 | D5: 74 | E5: 84 | F5: 43821 | G5: =AVERAGE(C5:E5) -> 75.333333 | H5: =IF(G5>=75,"A", IF(G5>=60,"B", IF(G5>=35,"C","F"))) -> A | I5: =IF('Students Grade'!$G5>=35,"Pass","Fail") -> Pass | J5: =COUNTIF(G5:G21,">60") -> 13 | K5: =COUNTIFS(C5:C23,">50") -> 15 | L5: =IF(OR(C5>=90,D5>=90,E5>=90),"Eligible","Not Eligible") -> Not Eligible
A6: 1006 | B6: Student 6 | C6: 80 | D6: 70 | E6: 65 | F6: 44001 | G6: =AVERAGE(C6:E6) -> 71.666667 | H6: =IF(G6>=75,"A", IF(G6>=60,"B", IF(G6>=35,"C","F"))) -> B | I6: =IF('Students Grade'!$G6>=35,"Pass","Fail") -> Pass | J6: =COUNTIF(G6:G22,">60") -> 12 | K6: =COUNTIFS(C6:C23,">50") -> 14 | L6: =IF(OR(C6>=90,D6>=90,E6>=90),"Eligible","Not Eligible") -> Not Eligible
A7: 1007 | B7: Student 7 | C7: 75 | D7: 47 | E7: 78 | F7: 44181 | G7: =AVERAGE(C7:E7) -> 66.666667 | H7: =IF(G7>=75,"A", IF(G7>=60,"B", IF(G7>=35,"C","F"))) -> B | I7: =IF('Students Grade'!$G7>=35,"Pass","Fail") -> Pass | J7: =COUNTIF(G7:G23,">60") -> 11 | K7: =COUNTIFS(C7:C24,">50") -> 13 | L7: =IF(OR(C7>=90,D7>=90,E7>=90),"Eligible","Not Eligible") -> Not Eligible
A8: 1008 | B8: Student 8 | C8: 94 | D8: 67 | E8: 64 | F8: 44361 | G8: =AVERAGE(C8:E8) -> 75 | H8: =IF(G8>=75,"A", IF(G8>=60,"B", IF(G8>=35,"C","F"))) -> A | I8: =IF('Students Grade'!$G8>=35,"Pass","Fail") -> Pass | J8: =COUNTIF(G8:G23,">60") -> 10 | K8: =COUNTIFS(C8:C26,">50") -> 12 | L8: =IF(OR(C8>=90,D8>=90,E8>=90),"Eligible","Not Eligible") -> Eligible
A9: 1009 | B9: Student 9 | C9: 41 | D9: 75 | E9: 56 | F9: 44541 | G9: =AVERAGE(C9:E9) -> 57.333333 | H9: =IF(G9>=75,"A", IF(G9>=60,"B", IF(G9>=35,"C","F"))) -> C | I9: =IF('Students Grade'!$G9>=35,"Pass","Fail") -> Pass | J9: =COUNTIF(G9:G24,">60") -> 10 | K9: =COUNTIFS(C9:C27,">50") -> 11 | L9: =IF(OR(C9>=90,D9>=90,E9>=90),"Eligible","Not Eligible") -> Not Eligible
A10: 1010 | B10: Student 10 | C10: 98 | D10: 54 | E10: 58 | F10: 44721 | G10: =AVERAGE(C10:E10) -> 70 | H10: =IF(G10>=75,"A", IF(G10>=60,"B", IF(G10>=35,"C","F"))) -> B | I10: =IF('Students Grade'!$G10>=35,"Pass","Fail") -> Pass | J10: =COUNTIF(G10:G26,">60") -> 11 | K10: =COUNTIFS(C10:C28,">50") -> 11 | L10: =IF(OR(C10>=90,D10>=90,E10>=90),"Eligible","Not Eligible") -> Eligible
A11: 1011 | B11: Student 11 | C11: 73 | D11: 79 | E11: 53 | F11: 44901 | G11: =AVERAGE(C11:E11) -> 68.333333 | H11: =IF(G11>=75,"A", IF(G11>=60,"B", IF(G11>=35,"C","F"))) -> B | I11: =IF('Students Grade'!$G11>=35,"Pass","Fail") -> Pass | J11: =COUNTIF(G11:G27,">60") -> 10 | K11: =COUNTIFS(C11:C29,">50") -> 10 | L11: =IF(OR(C11>=90,D11>=90,E11>=90),"Eligible","Not Eligible") -> Not Eligible
A12: 1012 | B12: Student 12 | C12: 85 | D12: 89 | E12: 79 | F12: 45081 | G12: =AVERAGE(C12:E12) -> 84.333333 | H12: =IF(G12>=75,"A", IF(G12>=60,"B", IF(G12>=35,"C","F"))) -> A | I12: =IF('Students Grade'!$G12>=35,"Pass","Fail") -> Pass | J12: =COUNTIF(G12:G28,">60") -> 9 | K12: =COUNTIFS(C12:C30,">50") -> 9 | L12: =IF(OR(C12>=90,D12>=90,E12>=90),"Eligible","Not Eligible") -> Not Eligible
A13: 1013 | B13: Student 13 | C13: 98 | D13: 90 | E13: 97 | F13: 45261 | G13: =AVERAGE(C13:E13) -> 95 | H13: =IF(G13>=75,"A", IF(G13>=60,"B", IF(G13>=35,"C","F"))) -> A | I13: =IF('Students Grade'!$G13>=35,"Pass","Fail") -> Pass | J13: =COUNTIF(G13:G29,">60") -> 8 | K13: =COUNTIFS(C13:C31,">50") -> 8 | L13: =IF(OR(C13>=90,D13>=90,E13>=90),"Eligible","Not Eligible") -> Eligible
A14: 1014 | B14: Student 14 | C14: 93 | D14: 40 | E14: 44 | F14: 45441 | G14: =AVERAGE(C14:E14) -> 59 | H14: =IF(G14>=75,"A", IF(G14>=60,"B", IF(G14>=35,"C","F"))) -> C | I14: =IF('Students Grade'!$G14>=35,"Pass","Fail") -> Pass | J14: =COUNTIF(G14:G30,">60") -> 7 | K14: =COUNTIFS(C14:C32,">50") -> 7 | L14: =IF(OR(C14>=90,D14>=90,E14>=90),"Eligible","Not Eligible") -> Eligible
A15: 1015 | B15: Student 15 | C15: 70 | D15: 51 | E15: 75 | F15: 45621 | G15: =AVERAGE(C15:E15) -> 65.333333 | H15: =IF(G15>=75,"A", IF(G15>=60,"B", IF(G15>=35,"C","F"))) -> B | I15: =IF('Students Grade'!$G15>=35,"Pass","Fail") -> Pass | J15: =COUNTIF(G15:G31,">60") -> 7 | K15: =COUNTIFS(C15:C33,">50") -> 6 | L15: =IF(OR(C15>=90,D15>=90,E15>=90),"Eligible","Not Eligible") -> Not Eligible
A16: 1016 | B16: Student 16 | C16: 98 | D16: 77 | E16: 60 | F16: 45801 | G16: =AVERAGE(C16:E16) -> 78.333333 | H16: =IF(G16>=75,"A", IF(G16>=60,"B", IF(G16>=35,"C","F"))) -> A | I16: =IF('Students Grade'!$G16>=35,"Pass","Fail") -> Pass | J16: =COUNTIF(G16:G32,">60") -> 6 | K16: =COUNTIFS(C16:C34,">50") -> 5 | L16: =IF(OR(C16>=90,D16>=90,E16>=90),"Eligible","Not Eligible") -> Eligible
A17: 1017 | B17: Student 17 | C17: 66 | D17: 59 | E17: 40 | F17: 45981 | G17: =AVERAGE(C17:E17) -> 55 | H17: =IF(G17>=75,"A", IF(G17>=60,"B", IF(G17>=35,"C","F"))) -> C | I17: =IF('Students Grade'!$G17>=35,"Pass","Fail") -> Pass | J17: =COUNTIF(G17:G33,">60") -> 5 | K17: =COUNTIFS(C17:C35,">50") -> 4 | L17: =IF(OR(C17>=90,D17>=90,E17>=90),"Eligible","Not Eligible") -> Not Eligible
A18: 1018 | B18: Student 18 | C18: 82 | D18: 48 | E18: 79 | F18: 46161 | G18: =AVERAGE(C18:E18) -> 69.666667 | H18: =IF(G18>=75,"A", IF(G18>=60,"B", IF(G18>=35,"C","F"))) -> B | I18: =IF('Students Grade'!$G18>=35,"Pass","Fail") -> Pass | J18: =COUNTIF(G18:G34,">60") -> 5 | K18: =COUNTIFS(C18:C36,">50") -> 3 | L18: =IF(OR(C18>=90,D18>=90,E18>=90),"Eligible","Not Eligible") -> Not Eligible
A19: 1019 | B19: Student 19 | C19: 90 | D19: 78 | E19: 60 | F19: 46341 | G19: =AVERAGE(C19:E19) -> 76 | H19: =IF(G19>=75,"A", IF(G19>=60,"B", IF(G19>=35,"C","F"))) -> A | I19: =IF('Students Grade'!$G19>=35,"Pass","Fail") -> Pass | J19: =COUNTIF(G19:G35,">60") -> 4 | K19: =COUNTIFS(C19:C37,">50") -> 2 | L19: =IF(OR(C19>=90,D19>=90,E19>=90),"Eligible","Not Eligible") -> Eligible
A20: 1020 | B20: Student 20 | C20: 83 | D20: 92 | E20: 55 | F20: 46521 | G20: =AVERAGE(C20:E20) -> 76.666667 | H20: =IF(G20>=75,"A", IF(G20>=60,"B", IF(G20>=35,"C","F"))) -> A | I20: =IF('Students Grade'!$G20>=35,"Pass","Fail") -> Pass | J20: =COUNTIF(G20:G36,">60") -> 3 | K20: =COUNTIFS(C20:C38,">50") -> 1 | L20: =IF(OR(C20>=90,D20>=90,E20>=90),"Eligible","Not Eligible") -> Eligible
F22: Above 80 marks | G22: =COUNTIF(G2:G20,">80") -> 2
F24: Above 60 Average | G24: =AVERAGEIFS(C2:C20, C2:C20, ">60") -> 83.444444
F26: Roundup Values | G26: =ROUNDUP(G24,2) -> 83.45

Sheet Sales Data
K1: Vlookup Functions Fatched Sales by using vlookup | M1: Compute discounts
A2: Sales ID | B2: Product | C2: Region | D2: Salesperson | E2: Amount | F2: Date | G2: Extract Month & year from Data | H2: Upper | I2: Lower | J2: Left & find | K2: Sales ID | L2: Sales Amount
A3: 2001 | B3: Keyboard | C3: South | D3: Person 1 | E3: 7048 | F3: 44927 | G3: =TEXT(F3,"mmm-yyyy") -> Jan-2023 | H3: =UPPER(D3) -> PERSON 1 | I3: =LOWER(D3) -> person 1 | J3: =LEFT(D3, FIND(" ", D3 & " ") - 1) -> Person | K3: 2001 | L3: =VLOOKUP(K3,$A$2:$E$22,5,0) -> 7048 | M3: =IF(E3>=40000,20%,IF(E3>=30000,15%,IF(E3>=20000,10%,5%))) -> 0.05
A4: 2002 | B4: Printer | C4: West | D4: Person 2 | E4: 17428 | F4: 44942 | G4: =TEXT(F4,"mmm-yyyy") -> Jan-2023 | H4: =UPPER(D4) -> PERSON 2 | I4: =LOWER(D4) -> person 2 | J4: =LEFT(D4, FIND(" ", D4 & " ") - 1) -> Person | K4: 2002 | L4: =VLOOKUP(K4,$A$2:$E$22,5,0) -> 17428 | M4: =IF(E4>=40000,20%,IF(E4>=30000,15%,IF(E4>=20000,10%,5%))) -> 0.05
A5: 2003 | B5: Mouse | C5: South | D5: Person 3 | E5: 23672 | F5: 44957 | G5: =TEXT(F5,"mmm-yyyy") -> Jan-2023 | H5: =UPPER(D5) -> PERSON 3 | I5: =LOWER(D5) -> person 3 | J5: =LEFT(D5, FIND(" ", D5 & " ") - 1) -> Person | K5: 2003 | L5: =VLOOKUP(K5,$A$2:$E$22,5,0) -> 23672 | M5: =IF(E5>=40000,20%,IF(E5>=30000,15%,IF(E5>=20000,10%,5%))) -> 0.1
A6: 2004 | B6: Printer | C6: East | D6: Person 4 | E6: 5264 | F6: 44972 | G6: =TEXT(F6,"mmm-yyyy") -> Feb-2023 | H6: =UPPER(D6) -> PERSON 4 | I6: =LOWER(D6) -> person 4 | J6: =LEFT(D6, FIND(" ", D6 & " ") - 1) -> Person | K6: 2004 | L6: =VLOOKUP(K6,$A$2:$E$22,5,0) -> 5264 | M6: =IF(E6>=40000,20%,IF(E6>=30000,15%,IF(E6>=20000,10%,5%))) -> 0.05
A7: 2005 | B7: Keyboard | C7: North | D7: Person 5 | E7: 43388 | F7: 44987 | G7: =TEXT(F7,"mmm-yyyy") -> Mar-2023 | H7: =UPPER(D7) -> PERSON 5 | I7: =LOWER(D7) -> person 5 | J7: =LEFT(D7, FIND(" ", D7 & " ") - 1) -> Person | K7: 2005 | L7: =VLOOKUP(K7,$A$2:$E$22,5,0) -> 43388 | M7: =IF(E7>=40000,20%,IF(E7>=30000,15%,IF(E7>=20000,10%,5%))) -> 0.2
A8: 2006 | B8: Mouse | C8: North | D8: Person 6 | E8: 19757 | F8: 45002 | G8: =TEXT(F8,"mmm-yyyy") -> Mar-2023 | H8: =UPPER(D8) -> PERSON 6 | I8: =LOWER(D8) -> person 6 | J8: =LEFT(D8, FIND(" ", D8 & " ") - 1) -> Person | K8: 2006 | L8: =VLOOKUP(K8,$A$2:$E$22,5,0) -> 19757 | M8: =IF(E8>=40000,20%,IF(E8>=30000,15%,IF(E8>=20000,10%,5%))) -> 0.05
A9: 2007 | B9: Mouse | C9: East | D9: Person 7 | E9: 32058 | F9: 45017 | G9: =TEXT(F9,"mmm-yyyy") -> Apr-2023 | H9: =UPPER(D9) -> PERSON 7 | I9: =LOWER(D9) -> person 7 | J9: =LEFT(D9, FIND(" ", D9 & " ") - 1) -> Person | K9: 2007 | L9: =VLOOKUP(K9,$A$2:$E$22,5,0) -> 32058 | M9: =IF(E9>=40000,20%,IF(E9>=30000,15%,IF(E9>=20000,10%,5%))) -> 0.15
A10: 2008 | B10: Keyboard | C10: East | D10: Person 8 | E10: 46429 | F10: 45032 | G10: =TEXT(F10,"mmm-yyyy") -> Apr-2023 | H10: =UPPER(D10) -> PERSON 8 | I10: =LOWER(D10) -> person 8 | J10: =LEFT(D10, FIND(" ", D10 & " ") - 1) -> Person | K10: 2008 | L10: =VLOOKUP(K10,$A$2:$E$22,5,0) -> 46429 | M10: =IF(E10>=40000,20%,IF(E10>=30000,15%,IF(E10>=20000,10%,5%))) -> 0.2
A11: 2009 | B11: Printer | C11: East | D11: Person 9 | E11: 19746 | F11: 45047 | G11: =TEXT(F11,"mmm-yyyy") -> May-2023 | H11: =UPPER(D11) -> PERSON 9 | I11: =LOWER(D11) -> person 9 | J11: =LEFT(D11, FIND(" ", D11 & " ") - 1) -> Person | K11: 2009 | L11: =VLOOKUP(K11,$A$2:$E$22,5,0) -> 19746 | M11: =IF(E11>=40000,20%,IF(E11>=30000,15%,IF(E11>=20000,10%,5%))) -> 0.05
A12: 2010 | B12: Keyboard | C12: South | D12: Person 10 | E12: 35185 | F12: 45062 | G12: =TEXT(F12,"mmm-yyyy") -> May-2023 | H12: =UPPER(D12) -> PERSON 10 | I12: =LOWER(D12) -> person 10 | J12: =LEFT(D12, FIND(" ", D12 & " ") - 1) -> Person | K12: 2010 | L12: =VLOOKUP(K12,$A$2:$E$22,5,0) -> 35185 | M12: =IF(E12>=40000,20%,IF(E12>=30000,15%,IF(E12>=20000,10%,5%))) -> 0.15
A13: 2011 | B13: Keyboard | C13: East | D13: Person 11 | E13: 33920 | F13: 45077 | G13: =TEXT(F13,"mmm-yyyy") -> May-2023 | H13: =UPPER(D13) -> PERSON 11 | I13: =LOWER(D13) -> person 11 | J13: =LEFT(D13, FIND(" ", D13 & " ") - 1) -> Person | K13: 2011 | L13: =VLOOKUP(K13,$A$2:$E$22,5,0) -> 33920 | M13: =IF(E13>=40000,20%,IF(E13>=30000,15%,IF(E13>=20000,10%,5%))) -> 0.15
A14: 2012 | B14: Monitor | C14: North | D14: Person 12 | E14: 35611 | F14: 45092 | G14: =TEXT(F14,"mmm-yyyy") -> Jun-2023 | H14: =UPPER(D14) -> PERSON 12 | I14: =LOWER(D14) -> person 12 | J14: =LEFT(D14, FIND(" ", D14 & " ") - 1) -> Person | K14: 2012 | L14: =VLOOKUP(K14,$A$2:$E$22,5,0) -> 35611 | M14: =IF(E14>=40000,20%,IF(E14>=30000,15%,IF(E14>=20000,10%,5%))) -> 0.15
... A22: 2020 | B22: Printer | C22: West | D22: Person 20 | E22: 33953 | F22: 45212 | G22: =TEXT(F22,"mmm-yyyy") -> Oct-2023 | H22: =UPPER(D22) -> PERSON 20 | I22: =LOWER(D22) -> person 20 | J22: =LEFT(D22, FIND(" ", D22 & " ") - 1) -> Person | K22: 2020 | L22: =VLOOKUP(K22,$A$2:$E$22,5,0) -> 33953 | M22: =IF(E22>=40000,20%,IF(E22>=30000,15%,IF(E22>=20000,10%,5%))) -> 0.15
E23: =SUM(E3:E22) -> 507725
B25: SUBTOTAL | C25: =SUBTOTAL(9,E$3:E$22) -> 507725 | E25: Find the position of a product in a sales list. | H25: Last 5 trasitions sales Trends | I25: =SUM(OFFSET(E22,-4,0,5,1)) -> 149698
E26: Product | F26: Position
B27: Products wise and Region wise sales | C27: =SUMIFS(E2:E22, B2:B22,"Keyboard", C2:C22,"East") -> 80349 | E27: Keyboard | F27: =_xlfn.XMATCH(B3,$B$3:$B$22) -> 1
E28: Printer | F28: =_xlfn.XMATCH(B4,$B$3:$B$22) -> 2 | H28: Date of Birth | I28: 37103
E29: Mouse | F29: =_xlfn.XMATCH(B5,$B$3:$B$22) -> 3 | H29: Current Date | I29: =TODAY() -> 46038
B30: Index & Match | C30: Sales | E30: Printer | F30: =_xlfn.XMATCH(B6,$B$3:$B$22) -> 2 | H30: Current Time | I30: =NOW() -> 46038.58
B31: Person 1 | C31: {=INDEX(E:E, MATCH(1, (D:D=B31)*(G:G=B32), 0))} -> 7048 | E31: Keyboard | F31: =_xlfn.XMATCH(B7,$B$3:$B$22) -> 1
B32: Jan-2023 | H32: Age | I32: =DATEDIF(I28,TODAY(),"Y") -> 24

Sheet Employee Data
A1: Employee ID | B1: Name | C1: Department | D1: Salary | E1: Joining Date | F1: Extract year from joining date
A2: 3001 | B2: Employee 1 | C2: Finance | D2: 86766 | E2: 42005 | F2: =YEAR(E2) -> 2015
A3: 3002 | B3: Employee 2 | C3: Finance | D3: 31943 | E3: 42255 | F3: =YEAR(E3) -> 2015
A4: 3003 | B4: Employee 3 | C4: HR | D4: 63374 | E4: 42505 | F4: =YEAR(E4) -> 2016
A5: 3004 | B5: Employee 4 | C5: Finance | D5: 109972 | E5: 42755 | F5: =YEAR(E5) -> 2017
A6: 3005 | B6: Employee 5 | C6: IT | D6: 54149 | E6: 43005 | F6: =YEAR(E6) -> 2017
A7: 3006 | B7: Employee 6 | C7: IT | D7: 78689 | E7: 43255 | F7: =YEAR(E7) -> 2018 | H7: Employee ID | I7: Name | J7: Department | K7: Salary | L7: Joining Date
A8: 3007 | B8: Employee 7 | C8: Marketing | D8: 35960 | E8: 43505 | F8: =YEAR(E8) -> 2019 | H8: 3002 | I8: {=_xlfn.XLOOKUP(H8,A:A,B:E)} -> Employee 2 | J8: Finance | K8: 31943 | L8: 42255
A9: 3008 | B9: Employee 8 | C9: IT | D9: 91659 | E9: 43755 | F9: =YEAR(E9) -> 2019
A10: 3009 | B10: Employee 9 | C10: IT | D10: 90423 | E10: 44005 | F10: =YEAR(E10) -> 2020
A11: 3010 | B11: Employee 10 | C11: HR | D11: 107877 | E11: 44255 | F11: =YEAR(E11) -> 2021
A12: 3011 | B12: Employee 11 | C12: Finance | D12: 107634 | E12: 44505 | F12: =YEAR(E12) -> 2021
A13: 3012 | B13: Employee 12 | C13: Finance | D13: 35226 | E13: 44755 | F13: =YEAR(E13) -> 2022
A14: 3013 | B14: Employee 13 | C14: HR | D14: 40872 | E14: 45005 | F14: =YEAR(E14) -> 2023
A15: 3014 | B15: Employee 14 | C15: HR | D15: 55378 | E15: 45255 | F15: =YEAR(E15) -> 2023
A16: 3015 | B16: Employee 15 | C16: HR | D16: 63297 | E16: 45505 | F16: =YEAR(E16) -> 2024
A17: 3016 | B17: Employee 16 | C17: Finance | D17: 114173 | E17: 45755 | F17: =YEAR(E17) -> 2025
A18: 3017 | B18: Employee 17 | C18: HR | D18: 86915 | E18: 46005 | F18: =YEAR(E18) -> 2025
A19: 3018 | B19: Employee 18 | C19: IT | D19: 116284 | E19: 46255 | F19: =YEAR(E19) -> 2026
A20: 3019 | B20: Employee 19 | C20: Marketing | D20: 116283 | E20: 46505 | F20: =YEAR(E20) -> 2027
A21: 3020 | B21: Employee 20 | C21: Marketing | D21: 99924 | E21: 46755 | F21: =YEAR(E21) -> 2028
